gdparse/__init__.py
gdparse/core.py
gdparse-0.3.0.dist-info/METADATA
gdparse-0.3.0.dist-info/WHEEL
gdparse-0.3.0.dist-info/top_level.txt
gdparse-0.3.0.dist-info/RECORD
